LICENSE
MANIFEST.in
README.rst
setup.cfg
setup.py
django_oscar_pagseguro.egg-info/PKG-INFO
django_oscar_pagseguro.egg-info/SOURCES.txt
django_oscar_pagseguro.egg-info/dependency_links.txt
django_oscar_pagseguro.egg-info/requires.txt
django_oscar_pagseguro.egg-info/top_level.txt
oscar_pagseguro/__init__.py
oscar_pagseguro/signals.py
oscar_pagseguro/urls.py
oscar_pagseguro/views.py