Metadata-Version: 1.1
Name: django-oscar-pagseguro
Version: 0.0.4
Summary: Pagseguro integration for django-oscar
Home-page: https://github.com/daneoshiga/django-oscar-pagseguro
Author: Danilo Shiga
Author-email: daniloshiga@gmail.com
License: The MIT License (MIT)
